{
  "id": "https://openalex.org/I184999862",
  "ror": "https://ror.org/02f40zc51",
  "display_name": "Universidad de Salamanca",
  "country_code": "ES",
  "type": "education",
  "type_id": "https://openalex.org/institution-types/education",
  "lineage": [
    "https://openalex.org/I184999862"
  ],
  "homepage_url": "https://www.usal.es",
  "image_url": "https://commons.wikimedia.org/w/index.php?title=Special:Redirect/file/Logotipo%20Universidad%20de%20Salamanca.svg",
  "image_thumbnail_url": "https://commons.wikimedia.org/w/index.php?title=Special:Redirect/file/Logotipo%20Universidad%20de%20Salamanca.svg&width=300",
  "display_name_acronyms": [
    "USAL"
  ],
  "display_name_alternatives": [
    "Universidad de Salamanca",
    "University of Salamanca"
  ],
  "repositories": [
    {
      "id": "https://openalex.org/S4377196290",
      "display_name": "Gredos (University of Salamanca)",
      "host_organization": "https://openalex.org/I184999862",
      "host_organization_name": "Universidad de Salamanca",
      "host_organization_lineage": [
        "https://openalex.org/I184999862"
      ]
    }
  ],
  "works_count": 62478,
  "cited_by_count": 2612983,
  "summary_stats": {
    "2yr_mean_citedness": 1.764113423893394,
    "h_index": 388,
    "i10_index": 47942
  },
  "ids": {
    "openalex": "https://openalex.org/I184999862",
    "ror": "https://ror.org/02f40zc51",
    "grid": "grid.11762.33",
    "wikipedia": "http://en.wikipedia.org/wiki/University_of_Salamanca",
    "wikidata": "https://www.wikidata.org/wiki/Q308963"
  },
  "geo": {
    "city": "Salamanca",
    "geonames_city_id": "3111108",
    "region": null,
    "country_code": "ES",
    "country": "Spain",
    "latitude": 40.96881866455078,
    "longitude": -5.663879871368408
  },
  "international": {},
  "associated_institutions": [
    {
      "id": "https://openalex.org/I4210099034",
      "ror": "https://ror.org/0131vfw26",
      "display_name": "Complejo Hospitalario de Salamanca",
      "country_code": "ES",
      "type": "healthcare",
      "relationship": "child"
    },
    {
      "id": "https://openalex.org/I4210134045",
      "ror": "https://ror.org/03em6xj44",
      "display_name": "Instituto de Investigación Biomédica de Salamanca",
      "country_code": "ES",
      "type": "facility",
      "relationship": "child"
    },
    {
      "id": "https://openalex.org/I4210138819",
      "ror": "https://ror.org/04rxrdv16",
      "display_name": "Centro de Investigación del Cáncer",
      "country_code": "ES",
      "type": "facility",
      "relationship": "child"
    },
    {
      "id": "https://openalex.org/I4210154586",
      "ror": "https://ror.org/055cmx385",
      "display_name": "Instituto de Biología Funcional y Genómica",
      "country_code": "ES",
      "type": "facility",
      "relationship": "child"
    },
    {
      "id": "https://openalex.org/I4387154232",
      "ror": "https://ror.org/00g3fjr10",
      "display_name": "AIR Institute",
      "country_code": null,
      "type": "nonprofit",
      "relationship": "related"
    },
    {
      "id": "https://openalex.org/I4387156156",
      "ror": "https://ror.org/03fwfk305",
      "display_name": "Instituto de Neurociencias de Castilla y León",
      "country_code": null,
      "type": "facility",
      "relationship": "child"
    },
    {
      "id": "https://openalex.org/I4388891778",
      "ror": "https://ror.org/043vr8e29",
      "display_name": "Instituto de Biología Molecular y Celular del Cáncer de Salamanca",
      "country_code": null,
      "type": "facility",
      "relationship": "child"
    },
    {
      "id": "https://openalex.org/I4388891829",
      "ror": "https://ror.org/00gjnn020",
      "display_name": "Instituto Universitario de Integración en la Comunidad",
      "country_code": null,
      "type": "education",
      "relationship": "child"
    },
    {
      "id": "https://openalex.org/I4392021127",
      "ror": "https://ror.org/00xnj6419",
      "display_name": "Instituto Universitario de Ciencias de la Educación",
      "country_code": null,
      "type": "facility",
      "relationship": "child"
    }
  ],
  "counts_by_year": [
    {
      "year": 2026,
      "works_count": 1059,
      "oa_works_count": 879,
      "cited_by_count": 165
    },
    {
      "year": 2025,
      "works_count": 4192,
      "oa_works_count": 3394,
      "cited_by_count": 3514
    },
    {
      "year": 2024,
      "works_count": 4034,
      "oa_works_count": 3432,
      "cited_by_count": 12196
    },
    {
      "year": 2023,
      "works_count": 4329,
      "oa_works_count": 3572,
      "cited_by_count": 22002
    },
    {
      "year": 2022,
      "works_count": 3887,
      "oa_works_count": 3246,
      "cited_by_count": 30710
    },
    {
      "year": 2021,
      "works_count": 3806,
      "oa_works_count": 2941,
      "cited_by_count": 45636
    },
    {
      "year": 2020,
      "works_count": 3744,
      "oa_works_count": 2846,
      "cited_by_count": 53360
    },
    {
      "year": 2019,
      "works_count": 3390,
      "oa_works_count": 2456,
      "cited_by_count": 49917
    },
    {
      "year": 2018,
      "works_count": 3043,
      "oa_works_count": 2171,
      "cited_by_count": 43882
    },
    {
      "year": 2017,
      "works_count": 2842,
      "oa_works_count": 1977,
      "cited_by_count": 46982
    },
    {
      "year": 2016,
      "works_count": 2771,
      "oa_works_count": 1832,
      "cited_by_count": 52647
    },
    {
      "year": 2015,
      "works_count": 2220,
      "oa_works_count": 1333,
      "cited_by_count": 65743
    },
    {
      "year": 2014,
      "works_count": 2135,
      "oa_works_count": 1252,
      "cited_by_count": 60107
    },
    {
      "year": 2013,
      "works_count": 2364,
      "oa_works_count": 1445,
      "cited_by_count": 43246
    },
    {
      "year": 2012,
      "works_count": 1728,
      "oa_works_count": 979,
      "cited_by_count": 44272
    },
    {
      "year": 2011,
      "works_count": 1671,
      "oa_works_count": 921,
      "cited_by_count": 45462
    },
    {
      "year": 2010,
      "works_count": 1637,
      "oa_works_count": 801,
      "cited_by_count": 39161
    }
  ],
  "roles": [
    {
      "role": "funder",
      "id": "https://openalex.org/F4320328269",
      "works_count": 1805
    },
    {
      "role": "institution",
      "id": "https://openalex.org/I184999862",
      "works_count": 62478
    },
    {
      "role": "publisher",
      "id": "https://openalex.org/P4310321104",
      "works_count": 1573
    }
  ],
  "topics": [
    {
      "id": "https://openalex.org/T14246",
      "display_name": "E-Learning and Knowledge Management",
      "count": 1812,
      "score": 0.9998999834060669,
      "subfield": {
        "id": "https://openalex.org/subfields/1706",
        "display_name": "Computer Science Applications"
      },
      "field": {
        "id": "https://openalex.org/fields/17",
        "display_name": "Computer Science"
      },
      "domain": {
        "id": "https://openalex.org/domains/3",
        "display_name": "Physical Sciences"
      }
    },
    {
      "id": "https://openalex.org/T12395",
      "display_name": "Educational Innovations and Technology",
      "count": 1021,
      "score": 0.9997000098228455,
      "subfield": {
        "id": "https://openalex.org/subfields/1710",
        "display_name": "Information Systems"
      },
      "field": {
        "id": "https://openalex.org/fields/17",
        "display_name": "Computer Science"
      },
      "domain": {
        "id": "https://openalex.org/domains/3",
        "display_name": "Physical Sciences"
      }
    },
    {
      "id": "https://openalex.org/T13624",
      "display_name": "Social Sciences and Policies",
      "count": 783,
      "score": 0.9998999834060669,
      "subfield": {
        "id": "https://openalex.org/subfields/3300",
        "display_name": "General Social Sciences"
      },
      "field": {
        "id": "https://openalex.org/fields/33",
        "display_name": "Social Sciences"
      },
      "domain": {
        "id": "https://openalex.org/domains/2",
        "display_name": "Social Sciences"
      }
    },
    {
      "id": "https://openalex.org/T10017",
      "display_name": "Geology and Paleoclimatology Research",
      "count": 746,
      "score": 1.0,
      "subfield": {
        "id": "https://openalex.org/subfields/1902",
        "display_name": "Atmospheric Science"
      },
      "field": {
        "id": "https://openalex.org/fields/19",
        "display_name": "Earth and Planetary Sciences"
      },
      "domain": {
        "id": "https://openalex.org/domains/3",
        "display_name": "Physical Sciences"
      }
    },
    {
      "id": "https://openalex.org/T13392",
      "display_name": "History of Education in Spain",
      "count": 709,
      "score": 1.0,
      "subfield": {
        "id": "https://openalex.org/subfields/1202",
        "display_name": "History"
      },
      "field": {
        "id": "https://openalex.org/fields/12",
        "display_name": "Arts and Humanities"
      },
      "domain": {
        "id": "https://openalex.org/domains/2",
        "display_name": "Social Sciences"
      }
    },
    {
      "id": "https://openalex.org/T11857",
      "display_name": "Archaeological and Historical Studies",
      "count": 703,
      "score": 1.0,
      "subfield": {
        "id": "https://openalex.org/subfields/1204",
        "display_name": "Archeology"
      },
      "field": {
        "id": "https://openalex.org/fields/12",
        "display_name": "Arts and Humanities"
      },
      "domain": {
        "id": "https://openalex.org/domains/2",
        "display_name": "Social Sciences"
      }
    },
    {
      "id": "https://openalex.org/T10649",
      "display_name": "Multiple Myeloma Research and Treatments",
      "count": 659,
      "score": 1.0,
      "subfield": {
        "id": "https://openalex.org/subfields/2720",
        "display_name": "Hematology"
      },
      "field": {
        "id": "https://openalex.org/fields/27",
        "display_name": "Medicine"
      },
      "domain": {
        "id": "https://openalex.org/domains/4",
        "display_name": "Health Sciences"
      }
    },
    {
      "id": "https://openalex.org/T12341",
      "display_name": "Spanish Linguistics and Language Studies",
      "count": 658,
      "score": 0.9998000264167786,
      "subfield": {
        "id": "https://openalex.org/subfields/1203",
        "display_name": "Language and Linguistics"
      },
      "field": {
        "id": "https://openalex.org/fields/12",
        "display_name": "Arts and Humanities"
      },
      "domain": {
        "id": "https://openalex.org/domains/2",
        "display_name": "Social Sciences"
      }
    },
    {
      "id": "https://openalex.org/T13205",
      "display_name": "Geological and Geophysical Studies Worldwide",
      "count": 654,
      "score": 1.0,
      "subfield": {
        "id": "https://openalex.org/subfields/1908",
        "display_name": "Geophysics"
      },
      "field": {
        "id": "https://openalex.org/fields/19",
        "display_name": "Earth and Planetary Sciences"
      },
      "domain": {
        "id": "https://openalex.org/domains/3",
        "display_name": "Physical Sciences"
      }
    },
    {
      "id": "https://openalex.org/T14490",
      "display_name": "Human Rights and Immigration",
      "count": 621,
      "score": 0.9994999766349792,
      "subfield": {
        "id": "https://openalex.org/subfields/3312",
        "display_name": "Sociology and Political Science"
      },
      "field": {
        "id": "https://openalex.org/fields/33",
        "display_name": "Social Sciences"
      },
      "domain": {
        "id": "https://openalex.org/domains/2",
        "display_name": "Social Sciences"
      }
    },
    {
      "id": "https://openalex.org/T10224",
      "display_name": "Quantum Chromodynamics and Particle Interactions",
      "count": 606,
      "score": 1.0,
      "subfield": {
        "id": "https://openalex.org/subfields/3106",
        "display_name": "Nuclear and High Energy Physics"
      },
      "field": {
        "id": "https://openalex.org/fields/31",
        "display_name": "Physics and Astronomy"
      },
      "domain": {
        "id": "https://openalex.org/domains/3",
        "display_name": "Physical Sciences"
      }
    },
    {
      "id": "https://openalex.org/T10001",
      "display_name": "Geological and Geochemical Analysis",
      "count": 541,
      "score": 1.0,
      "subfield": {
        "id": "https://openalex.org/subfields/1908",
        "display_name": "Geophysics"
      },
      "field": {
        "id": "https://openalex.org/fields/19",
        "display_name": "Earth and Planetary Sciences"
      },
      "domain": {
        "id": "https://openalex.org/domains/3",
        "display_name": "Physical Sciences"
      }
    },
    {
      "id": "https://openalex.org/T12332",
      "display_name": "Comparative constitutional jurisprudence studies",
      "count": 532,
      "score": 0.9994000196456909,
      "subfield": {
        "id": "https://openalex.org/subfields/3320",
        "display_name": "Political Science and International Relations"
      },
      "field": {
        "id": "https://openalex.org/fields/33",
        "display_name": "Social Sciences"
      },
      "domain": {
        "id": "https://openalex.org/domains/2",
        "display_name": "Social Sciences"
      }
    },
    {
      "id": "https://openalex.org/T10566",
      "display_name": "Laser-Matter Interactions and Applications",
      "count": 523,
      "score": 1.0,
      "subfield": {
        "id": "https://openalex.org/subfields/3107",
        "display_name": "Atomic and Molecular Physics, and Optics"
      },
      "field": {
        "id": "https://openalex.org/fields/31",
        "display_name": "Physics and Astronomy"
      },
      "domain": {
        "id": "https://openalex.org/domains/3",
        "display_name": "Physical Sciences"
      }
    },
    {
      "id": "https://openalex.org/T13714",
      "display_name": "Medieval Architecture and Archaeology",
      "count": 519,
      "score": 1.0,
      "subfield": {
        "id": "https://openalex.org/subfields/1204",
        "display_name": "Archeology"
      },
      "field": {
        "id": "https://openalex.org/fields/12",
        "display_name": "Arts and Humanities"
      },
      "domain": {
        "id": "https://openalex.org/domains/2",
        "display_name": "Social Sciences"
      }
    },
    {
      "id": "https://openalex.org/T12217",
      "display_name": "Higher Education Teaching and Evaluation",
      "count": 517,
      "score": 0.9998999834060669,
      "subfield": {
        "id": "https://openalex.org/subfields/3304",
        "display_name": "Education"
      },
      "field": {
        "id": "https://openalex.org/fields/33",
        "display_name": "Social Sciences"
      },
      "domain": {
        "id": "https://openalex.org/domains/2",
        "display_name": "Social Sciences"
      }
    },
    {
      "id": "https://openalex.org/T11157",
      "display_name": "Chronic Lymphocytic Leukemia Research",
      "count": 515,
      "score": 1.0,
      "subfield": {
        "id": "https://openalex.org/subfields/2716",
        "display_name": "Genetics"
      },
      "field": {
        "id": "https://openalex.org/fields/27",
        "display_name": "Medicine"
      },
      "domain": {
        "id": "https://openalex.org/domains/4",
        "display_name": "Health Sciences"
      }
    },
    {
      "id": "https://openalex.org/T13147",
      "display_name": "Ethics and bioethics in healthcare",
      "count": 515,
      "score": 0.9998000264167786,
      "subfield": {
        "id": "https://openalex.org/subfields/2739",
        "display_name": "Public Health, Environmental and Occupational Health"
      },
      "field": {
        "id": "https://openalex.org/fields/27",
        "display_name": "Medicine"
      },
      "domain": {
        "id": "https://openalex.org/domains/4",
        "display_name": "Health Sciences"
      }
    },
    {
      "id": "https://openalex.org/T10095",
      "display_name": "Cosmology and Gravitation Theories",
      "count": 513,
      "score": 1.0,
      "subfield": {
        "id": "https://openalex.org/subfields/3103",
        "display_name": "Astronomy and Astrophysics"
      },
      "field": {
        "id": "https://openalex.org/fields/31",
        "display_name": "Physics and Astronomy"
      },
      "domain": {
        "id": "https://openalex.org/domains/3",
        "display_name": "Physical Sciences"
      }
    },
    {
      "id": "https://openalex.org/T10048",
      "display_name": "Particle physics theoretical and experimental studies",
      "count": 506,
      "score": 1.0,
      "subfield": {
        "id": "https://openalex.org/subfields/3106",
        "display_name": "Nuclear and High Energy Physics"
      },
      "field": {
        "id": "https://openalex.org/fields/31",
        "display_name": "Physics and Astronomy"
      },
      "domain": {
        "id": "https://openalex.org/domains/3",
        "display_name": "Physical Sciences"
      }
    },
    {
      "id": "https://openalex.org/T10309",
      "display_name": "Acute Myeloid Leukemia Research",
      "count": 483,
      "score": 1.0,
      "subfield": {
        "id": "https://openalex.org/subfields/2720",
        "display_name": "Hematology"
      },
      "field": {
        "id": "https://openalex.org/fields/27",
        "display_name": "Medicine"
      },
      "domain": {
        "id": "https://openalex.org/domains/4",
        "display_name": "Health Sciences"
      }
    },
    {
      "id": "https://openalex.org/T14061",
      "display_name": "Educational Practices and Policies",
      "count": 480,
      "score": 1.0,
      "subfield": {
        "id": "https://openalex.org/subfields/3304",
        "display_name": "Education"
      },
      "field": {
        "id": "https://openalex.org/fields/33",
        "display_name": "Social Sciences"
      },
      "domain": {
        "id": "https://openalex.org/domains/2",
        "display_name": "Social Sciences"
      }
    },
    {
      "id": "https://openalex.org/T14386",
      "display_name": "Libraries, Manuscripts, and Books",
      "count": 468,
      "score": 0.9990000128746033,
      "subfield": {
        "id": "https://openalex.org/subfields/1202",
        "display_name": "History"
      },
      "field": {
        "id": "https://openalex.org/fields/12",
        "display_name": "Arts and Humanities"
      },
      "domain": {
        "id": "https://openalex.org/domains/2",
        "display_name": "Social Sciences"
      }
    },
    {
      "id": "https://openalex.org/T13831",
      "display_name": "Archaeological and Geological Studies",
      "count": 464,
      "score": 1.0,
      "subfield": {
        "id": "https://openalex.org/subfields/1204",
        "display_name": "Archeology"
      },
      "field": {
        "id": "https://openalex.org/fields/12",
        "display_name": "Arts and Humanities"
      },
      "domain": {
        "id": "https://openalex.org/domains/2",
        "display_name": "Social Sciences"
      }
    },
    {
      "id": "https://openalex.org/T10497",
      "display_name": "Fungal and yeast genetics research",
      "count": 459,
      "score": 1.0,
      "subfield": {
        "id": "https://openalex.org/subfields/1312",
        "display_name": "Molecular Biology"
      },
      "field": {
        "id": "https://openalex.org/fields/13",
        "display_name": "Biochemistry, Genetics and Molecular Biology"
      },
      "domain": {
        "id": "https://openalex.org/domains/1",
        "display_name": "Life Sciences"
      }
    }
  ],
  "topic_share": [
    {
      "id": "https://openalex.org/T13392",
      "display_name": "History of Education in Spain",
      "value": 0.0318009,
      "subfield": {
        "id": "https://openalex.org/subfields/1202",
        "display_name": "History"
      },
      "field": {
        "id": "https://openalex.org/fields/12",
        "display_name": "Arts and Humanities"
      },
      "domain": {
        "id": "https://openalex.org/domains/2",
        "display_name": "Social Sciences"
      }
    },
    {
      "id": "https://openalex.org/T14498",
      "display_name": "Educational Technology in Learning",
      "value": 0.0178783,
      "subfield": {
        "id": "https://openalex.org/subfields/1710",
        "display_name": "Information Systems"
      },
      "field": {
        "id": "https://openalex.org/fields/17",
        "display_name": "Computer Science"
      },
      "domain": {
        "id": "https://openalex.org/domains/3",
        "display_name": "Physical Sciences"
      }
    },
    {
      "id": "https://openalex.org/T14246",
      "display_name": "E-Learning and Knowledge Management",
      "value": 0.0178608,
      "subfield": {
        "id": "https://openalex.org/subfields/1706",
        "display_name": "Computer Science Applications"
      },
      "field": {
        "id": "https://openalex.org/fields/17",
        "display_name": "Computer Science"
      },
      "domain": {
        "id": "https://openalex.org/domains/3",
        "display_name": "Physical Sciences"
      }
    },
    {
      "id": "https://openalex.org/T13462",
      "display_name": "Spanish Philosophy and Literature",
      "value": 0.0176605,
      "subfield": {
        "id": "https://openalex.org/subfields/1211",
        "display_name": "Philosophy"
      },
      "field": {
        "id": "https://openalex.org/fields/12",
        "display_name": "Arts and Humanities"
      },
      "domain": {
        "id": "https://openalex.org/domains/2",
        "display_name": "Social Sciences"
      }
    },
    {
      "id": "https://openalex.org/T13195",
      "display_name": "Medieval Iberian Studies",
      "value": 0.0168609,
      "subfield": {
        "id": "https://openalex.org/subfields/1205",
        "display_name": "Classics"
      },
      "field": {
        "id": "https://openalex.org/fields/12",
        "display_name": "Arts and Humanities"
      },
      "domain": {
        "id": "https://openalex.org/domains/2",
        "display_name": "Social Sciences"
      }
    },
    {
      "id": "https://openalex.org/T13089",
      "display_name": "Medieval and Early Modern Iberia",
      "value": 0.016768,
      "subfield": {
        "id": "https://openalex.org/subfields/1202",
        "display_name": "History"
      },
      "field": {
        "id": "https://openalex.org/fields/12",
        "display_name": "Arts and Humanities"
      },
      "domain": {
        "id": "https://openalex.org/domains/2",
        "display_name": "Social Sciences"
      }
    },
    {
      "id": "https://openalex.org/T12986",
      "display_name": "Administrative Law and Governance",
      "value": 0.0148005,
      "subfield": {
        "id": "https://openalex.org/subfields/3320",
        "display_name": "Political Science and International Relations"
      },
      "field": {
        "id": "https://openalex.org/fields/33",
        "display_name": "Social Sciences"
      },
      "domain": {
        "id": "https://openalex.org/domains/2",
        "display_name": "Social Sciences"
      }
    },
    {
      "id": "https://openalex.org/T14490",
      "display_name": "Human Rights and Immigration",
      "value": 0.0147223,
      "subfield": {
        "id": "https://openalex.org/subfields/3312",
        "display_name": "Sociology and Political Science"
      },
      "field": {
        "id": "https://openalex.org/fields/33",
        "display_name": "Social Sciences"
      },
      "domain": {
        "id": "https://openalex.org/domains/2",
        "display_name": "Social Sciences"
      }
    },
    {
      "id": "https://openalex.org/T14386",
      "display_name": "Libraries, Manuscripts, and Books",
      "value": 0.0141475,
      "subfield": {
        "id": "https://openalex.org/subfields/1202",
        "display_name": "History"
      },
      "field": {
        "id": "https://openalex.org/fields/12",
        "display_name": "Arts and Humanities"
      },
      "domain": {
        "id": "https://openalex.org/domains/2",
        "display_name": "Social Sciences"
      }
    },
    {
      "id": "https://openalex.org/T14003",
      "display_name": "Labor Law and Work Dynamics",
      "value": 0.0138189,
      "subfield": {
        "id": "https://openalex.org/subfields/3320",
        "display_name": "Political Science and International Relations"
      },
      "field": {
        "id": "https://openalex.org/fields/33",
        "display_name": "Social Sciences"
      },
      "domain": {
        "id": "https://openalex.org/domains/2",
        "display_name": "Social Sciences"
      }
    },
    {
      "id": "https://openalex.org/T13006",
      "display_name": "Spanish History and Politics",
      "value": 0.0137266,
      "subfield": {
        "id": "https://openalex.org/subfields/1202",
        "display_name": "History"
      },
      "field": {
        "id": "https://openalex.org/fields/12",
        "display_name": "Arts and Humanities"
      },
      "domain": {
        "id": "https://openalex.org/domains/2",
        "display_name": "Social Sciences"
      }
    },
    {
      "id": "https://openalex.org/T14442",
      "display_name": "Historical Studies in Science",
      "value": 0.0131835,
      "subfield": {
        "id": "https://openalex.org/subfields/1207",
        "display_name": "History and Philosophy of Science"
      },
      "field": {
        "id": "https://openalex.org/fields/12",
        "display_name": "Arts and Humanities"
      },
      "domain": {
        "id": "https://openalex.org/domains/2",
        "display_name": "Social Sciences"
      }
    },
    {
      "id": "https://openalex.org/T12743",
      "display_name": "Spanish Culture and Identity",
      "value": 0.0130052,
      "subfield": {
        "id": "https://openalex.org/subfields/1211",
        "display_name": "Philosophy"
      },
      "field": {
        "id": "https://openalex.org/fields/12",
        "display_name": "Arts and Humanities"
      },
      "domain": {
        "id": "https://openalex.org/domains/2",
        "display_name": "Social Sciences"
      }
    },
    {
      "id": "https://openalex.org/T13766",
      "display_name": "Media, Journalism, and Communication History",
      "value": 0.0129989,
      "subfield": {
        "id": "https://openalex.org/subfields/1202",
        "display_name": "History"
      },
      "field": {
        "id": "https://openalex.org/fields/12",
        "display_name": "Arts and Humanities"
      },
      "domain": {
        "id": "https://openalex.org/domains/2",
        "display_name": "Social Sciences"
      }
    },
    {
      "id": "https://openalex.org/T14267",
      "display_name": "Technology in Education and Healthcare",
      "value": 0.0128874,
      "subfield": {
        "id": "https://openalex.org/subfields/3304",
        "display_name": "Education"
      },
      "field": {
        "id": "https://openalex.org/fields/33",
        "display_name": "Social Sciences"
      },
      "domain": {
        "id": "https://openalex.org/domains/2",
        "display_name": "Social Sciences"
      }
    },
    {
      "id": "https://openalex.org/T11794",
      "display_name": "Early Modern Spanish Literature",
      "value": 0.012551,
      "subfield": {
        "id": "https://openalex.org/subfields/1208",
        "display_name": "Literature and Literary Theory"
      },
      "field": {
        "id": "https://openalex.org/fields/12",
        "display_name": "Arts and Humanities"
      },
      "domain": {
        "id": "https://openalex.org/domains/2",
        "display_name": "Social Sciences"
      }
    },
    {
      "id": "https://openalex.org/T14264",
      "display_name": "Law, Ethics, and AI Impact",
      "value": 0.0122263,
      "subfield": {
        "id": "https://openalex.org/subfields/1407",
        "display_name": "Organizational Behavior and Human Resource Management"
      },
      "field": {
        "id": "https://openalex.org/fields/14",
        "display_name": "Business, Management and Accounting"
      },
      "domain": {
        "id": "https://openalex.org/domains/2",
        "display_name": "Social Sciences"
      }
    },
    {
      "id": "https://openalex.org/T12803",
      "display_name": "Cinema History and Criticism",
      "value": 0.011989,
      "subfield": {
        "id": "https://openalex.org/subfields/1213",
        "display_name": "Visual Arts and Performing Arts"
      },
      "field": {
        "id": "https://openalex.org/fields/12",
        "display_name": "Arts and Humanities"
      },
      "domain": {
        "id": "https://openalex.org/domains/2",
        "display_name": "Social Sciences"
      }
    },
    {
      "id": "https://openalex.org/T11857",
      "display_name": "Archaeological and Historical Studies",
      "value": 0.0119381,
      "subfield": {
        "id": "https://openalex.org/subfields/1204",
        "display_name": "Archeology"
      },
      "field": {
        "id": "https://openalex.org/fields/12",
        "display_name": "Arts and Humanities"
      },
      "domain": {
        "id": "https://openalex.org/domains/2",
        "display_name": "Social Sciences"
      }
    },
    {
      "id": "https://openalex.org/T12217",
      "display_name": "Higher Education Teaching and Evaluation",
      "value": 0.0118209,
      "subfield": {
        "id": "https://openalex.org/subfields/3304",
        "display_name": "Education"
      },
      "field": {
        "id": "https://openalex.org/fields/33",
        "display_name": "Social Sciences"
      },
      "domain": {
        "id": "https://openalex.org/domains/2",
        "display_name": "Social Sciences"
      }
    },
    {
      "id": "https://openalex.org/T13831",
      "display_name": "Archaeological and Geological Studies",
      "value": 0.0117644,
      "subfield": {
        "id": "https://openalex.org/subfields/1204",
        "display_name": "Archeology"
      },
      "field": {
        "id": "https://openalex.org/fields/12",
        "display_name": "Arts and Humanities"
      },
      "domain": {
        "id": "https://openalex.org/domains/2",
        "display_name": "Social Sciences"
      }
    },
    {
      "id": "https://openalex.org/T13760",
      "display_name": "Finance, Taxation, and Governance",
      "value": 0.0116779,
      "subfield": {
        "id": "https://openalex.org/subfields/2308",
        "display_name": "Management, Monitoring, Policy and Law"
      },
      "field": {
        "id": "https://openalex.org/fields/23",
        "display_name": "Environmental Science"
      },
      "domain": {
        "id": "https://openalex.org/domains/3",
        "display_name": "Physical Sciences"
      }
    },
    {
      "id": "https://openalex.org/T14191",
      "display_name": "Historical Art and Architecture Studies",
      "value": 0.0116228,
      "subfield": {
        "id": "https://openalex.org/subfields/1206",
        "display_name": "Conservation"
      },
      "field": {
        "id": "https://openalex.org/fields/12",
        "display_name": "Arts and Humanities"
      },
      "domain": {
        "id": "https://openalex.org/domains/2",
        "display_name": "Social Sciences"
      }
    },
    {
      "id": "https://openalex.org/T12591",
      "display_name": "Inclusive Education and Diversity",
      "value": 0.011435,
      "subfield": {
        "id": "https://openalex.org/subfields/3304",
        "display_name": "Education"
      },
      "field": {
        "id": "https://openalex.org/fields/33",
        "display_name": "Social Sciences"
      },
      "domain": {
        "id": "https://openalex.org/domains/2",
        "display_name": "Social Sciences"
      }
    },
    {
      "id": "https://openalex.org/T14234",
      "display_name": "Data Privacy and Cybersecurity",
      "value": 0.0113838,
      "subfield": {
        "id": "https://openalex.org/subfields/3308",
        "display_name": "Law"
      },
      "field": {
        "id": "https://openalex.org/fields/33",
        "display_name": "Social Sciences"
      },
      "domain": {
        "id": "https://openalex.org/domains/2",
        "display_name": "Social Sciences"
      }
    }
  ],
  "is_super_system": false,
  "status": "active",
  "works_api_url": "https://api.openalex.org/works?filter=institutions.id:I184999862",
  "updated_date": "2026-03-28T06:00:04",
  "created_date": "2016-06-24T00:00:00"
}